MANIFEST.in
setup.cfg
setup.py
quicksearch/__init__.py
quicksearch/cli.py
quicksearch/launch.py
quicksearch.egg-info/PKG-INFO
quicksearch.egg-info/SOURCES.txt
quicksearch.egg-info/dependency_links.txt
quicksearch.egg-info/entry_points.txt
quicksearch.egg-info/not-zip-safe
quicksearch.egg-info/requires.txt
quicksearch.egg-info/top_level.txt
quicksearch/search_engines/500px.json
quicksearch/search_engines/8tracks.json
quicksearch/search_engines/__init__.py
quicksearch/search_engines/amazon.json
quicksearch/search_engines/archpkg.json
quicksearch/search_engines/archwiki.json
quicksearch/search_engines/arstechnica.json
quicksearch/search_engines/arxiv.json
quicksearch/search_engines/atmospherejs.json
quicksearch/search_engines/aur.json
quicksearch/search_engines/baidu.json
quicksearch/search_engines/bandcamp.json
quicksearch/search_engines/bgr.json
quicksearch/search_engines/bing.json
quicksearch/search_engines/buzzfeed.json
quicksearch/search_engines/cnn.json
quicksearch/search_engines/codepen.json
quicksearch/search_engines/coursera.json
quicksearch/search_engines/cplusplus.json
quicksearch/search_engines/crunchyroll.json
quicksearch/search_engines/debianpkg.json
quicksearch/search_engines/digg.json
quicksearch/search_engines/diigo.json
quicksearch/search_engines/dockerhub.json
quicksearch/search_engines/dribbble.json
quicksearch/search_engines/duckduckgo.json
quicksearch/search_engines/dumpert.json
quicksearch/search_engines/engadget.json
quicksearch/search_engines/facebook.json
quicksearch/search_engines/flickr.json
quicksearch/search_engines/flipkart.json
quicksearch/search_engines/foursquare.json
quicksearch/search_engines/gist.json
quicksearch/search_engines/github.json
quicksearch/search_engines/gmail.json
quicksearch/search_engines/go.json
quicksearch/search_engines/godoc.json
quicksearch/search_engines/google.json
quicksearch/search_engines/googledocs.json
quicksearch/search_engines/googleplus.json
quicksearch/search_engines/hackernews.json
quicksearch/search_engines/ietf.json
quicksearch/search_engines/ifttt.json
quicksearch/search_engines/imdb.json
quicksearch/search_engines/imgur.json
quicksearch/search_engines/inbox.json
quicksearch/search_engines/instagram.json
